sequencefolder.py
sequence_folder-0.2.dist-info/DESCRIPTION.rst
sequence_folder-0.2.dist-info/METADATA
sequence_folder-0.2.dist-info/RECORD
sequence_folder-0.2.dist-info/WHEEL
sequence_folder-0.2.dist-info/metadata.json
sequence_folder-0.2.dist-info/top_level.txt
