Metadata-Version: 2.0
Name: sequence-folder
Version: 0.2
Summary: Simple Python library to "make" multi dimension array from a sequence
Home-page: https://github.com/lel-amri/sequence-folder
Author: Léo El Amri
Author-email: leo@superlel.me
License: UNKNOWN
Platform: UNKNOWN
Classifier: Programming Language :: Python :: 3
Classifier: License :: OSI Approved :: MIT License
Classifier: Operating System :: OS Independent
